durable_streams/__init__.py
durable_streams/__main__.py
durable_streams-0.0.0.dist-info/licenses/LICENSE
durable_streams-0.0.0.dist-info/METADATA
durable_streams-0.0.0.dist-info/WHEEL
durable_streams-0.0.0.dist-info/entry_points.txt
durable_streams-0.0.0.dist-info/top_level.txt
durable_streams-0.0.0.dist-info/RECORD
